hyper_py/__init__.py
hyper_py/__main__.py
hyper_py/bkg_multigauss.py
hyper_py/bkg_single.py
hyper_py/config.py
hyper_py/create_background_slices.py
hyper_py/data_output.py
hyper_py/detection.py
hyper_py/extract_cubes.py
hyper_py/fitting.py
hyper_py/gaussfit.py
hyper_py/groups.py
hyper_py/hyper.py
hyper_py/logger.py
hyper_py/map_io.py
hyper_py/paths_io.py
hyper_py/photometry.py
hyper_py/run_hyper.py
hyper_py/single_map.py
hyper_py/survey.py
hyper_py/visualization.py
hyper_py/assets/default_config.yaml
hyper_py_photometry-1.0.0.dist-info/licenses/LICENSE
hyper_py_photometry-1.0.0.dist-info/METADATA
hyper_py_photometry-1.0.0.dist-info/WHEEL
hyper_py_photometry-1.0.0.dist-info/entry_points.txt
hyper_py_photometry-1.0.0.dist-info/top_level.txt
hyper_py_photometry-1.0.0.dist-info/RECORD
