Metadata-Version: 2.4
Name: hyper-py-photometry
Version: 1.0.0
Summary: HYPER: Hybrid Photometry Photometry and Extraction Routine
Author-email: Alessio Traficante <alessio.traficante@inaf.it>
Project-URL: Homepage, https://github.com/alessio-traficante/hyper-py
Requires-Python: >=3.11
License-File: LICENSE
Requires-Dist: pyyaml
Requires-Dist: astropy
Requires-Dist: numpy
Requires-Dist: photutils
Requires-Dist: scipy
Requires-Dist: lmfit
Requires-Dist: matplotlib
Requires-Dist: scikit-learn<1.6,>=1.4
Requires-Dist: ruamel.yaml>=0.18
Dynamic: license-file
